vp_suite/__about__.py
vp_suite/__init__.py
vp_suite/defaults.py
vp_suite/vpsuite.py
vp_suite/base/__init__.py
vp_suite/base/base_dataset.py
vp_suite/base/base_measure.py
vp_suite/base/base_model.py
vp_suite/base/base_model_block.py
vp_suite/datasets/__init__.py
vp_suite/datasets/bair.py
vp_suite/datasets/caltech_pedestrian.py
vp_suite/datasets/human36m.py
vp_suite/datasets/kitti_raw.py
vp_suite/datasets/kth.py
vp_suite/datasets/mmnist.py
vp_suite/datasets/mmnist_on_the_fly.py
vp_suite/datasets/physics101.py
vp_suite/datasets/synpick.py
vp_suite/measure/__init__.py
vp_suite/measure/image_wise.py
vp_suite/measure/loss_provider.py
vp_suite/measure/metric_provider.py
vp_suite/measure/fvd/__init__.py
vp_suite/measure/fvd/fvd.py
vp_suite/measure/fvd/_pytorch_i3d/__init__.py
vp_suite/measure/fvd/_pytorch_i3d/pytorch_i3d.py
vp_suite/model_blocks/__init__.py
vp_suite/model_blocks/conv.py
vp_suite/model_blocks/conv_lstm_hzzone.py
vp_suite/model_blocks/conv_lstm_ndrplz.py
vp_suite/model_blocks/enc.py
vp_suite/model_blocks/phydnet.py
vp_suite/model_blocks/predrnn.py
vp_suite/model_blocks/traj_gru.py
vp_suite/models/__init__.py
vp_suite/models/copy_last_frame.py
vp_suite/models/lstm.py
vp_suite/models/phydnet.py
vp_suite/models/predrnn_v2.py
vp_suite/models/st_phy.py
vp_suite/models/unet3d.py
vp_suite/models/precipitation_nowcasting/__init__.py
vp_suite/models/precipitation_nowcasting/ef_blocks.py
vp_suite/models/precipitation_nowcasting/ef_conv_lstm.py
vp_suite/models/precipitation_nowcasting/ef_traj_gru.py
vp_suite/resources/get_dataset_caltech_pedestrian.sh
vp_suite/resources/get_dataset_human36m.sh
vp_suite/resources/get_dataset_kitti_raw.sh
vp_suite/resources/get_dataset_kth.sh
vp_suite/resources/optuna_example_config.json
vp_suite/resources/set_run_path.py
vp_suite/utils/__init__.py
vp_suite/utils/compatibility.py
vp_suite/utils/dataset_wrapper.py
vp_suite/utils/models.py
vp_suite/utils/utils.py
vp_suite/utils/visualization.py
vp_suite-0.0.9.dist-info/LICENSE
vp_suite-0.0.9.dist-info/METADATA
vp_suite-0.0.9.dist-info/WHEEL
vp_suite-0.0.9.dist-info/top_level.txt
vp_suite-0.0.9.dist-info/RECORD
