Metadata-Version: 2.1
Name: vp-suite
Version: 0.0.9
Summary: A Framework for Training and Evaluating Video Prediction Models
Home-page: https://ais-bonn.github.io/vp-suite/
Download-URL: https://github.com/AIS-Bonn/vp-suite
Author: Andreas Boltres
Author-email: andreas.boltres@posteo.de
License: MIT
Project-URL: Documentation, https://ais-bonn.github.io/vp-suite/
Project-URL: Source, https://github.com/AIS-Bonn/vp-suite
Project-URL: Tracker, https://github.com/AIS-Bonn/vp-suite/issues
Keywords: deep learning,pytorch,AI,video prediction
Platform: UNKNOWN
Classifier: Environment :: Console
Classifier: Natural Language :: English
Classifier: Intended Audience :: Developers
Classifier: License :: OSI Approved :: MIT License
Classifier: Operating System :: OS Independent
Classifier: Programming Language :: Python :: 3 :: Only
Requires-Python: >=3.6
License-File: LICENSE
Requires-Dist: imageio (==2.13.4)
Requires-Dist: matplotlib (==3.5.1)
Requires-Dist: moviepy (==1.0.3)
Requires-Dist: numpy (==1.21.5)
Requires-Dist: opencv-python (==4.5.4.60)
Requires-Dist: optuna (==2.10.0)
Requires-Dist: Pillow (==9.0.1)
Requires-Dist: piqa (==1.1.7)
Requires-Dist: pytest (==6.2.5)
Requires-Dist: scipy (==1.7.3)
Requires-Dist: setuptools (==60.3.1)
Requires-Dist: tfrecord (==1.14.1)
Requires-Dist: torch (==1.10.1)
Requires-Dist: torchfile (==0.1.0)
Requires-Dist: torchvision (==0.11.2)
Requires-Dist: tqdm (==4.62.3)
Requires-Dist: wandb (==0.12.9)
Provides-Extra: dev
Requires-Dist: pytest ; extra == 'dev'
Requires-Dist: pytest-cov ; extra == 'dev'
Requires-Dist: sklearn ; extra == 'dev'
Requires-Dist: gitpython ; extra == 'dev'
Provides-Extra: doc
Requires-Dist: sphinx (==4.4.0) ; extra == 'doc'
Requires-Dist: sphinx-rtd-theme ; extra == 'doc'
Requires-Dist: sphinx-autodoc-typehints ; extra == 'doc'
Requires-Dist: m2r2 ; extra == 'doc'
Requires-Dist: tabulate ; extra == 'doc'
